LICENSE
setup.cfg
setup.py
comic_dl/__init__.py
comic_dl/__main__.py
comic_dl/__version__.py
comic_dl/comic_dl.py
comic_dl/configGenerator.py
comic_dl/exeMaker.py
comic_dl/globalFunctions.py
comic_dl/honcho.py
comic_dl.egg-info/PKG-INFO
comic_dl.egg-info/SOURCES.txt
comic_dl.egg-info/dependency_links.txt
comic_dl.egg-info/entry_points.txt
comic_dl.egg-info/top_level.txt
comic_dl/readcomiconline/RCO.py
comic_dl/readcomiconline/__init__.py
comic_dl/readcomiconline/dataUpdate.py
comic_dl/sites/__init__.py
comic_dl/sites/acQQ.py
comic_dl/sites/batoto.py
comic_dl/sites/comicNaver.py
comic_dl/sites/comicextra.py
comic_dl/sites/foolSlide.py
comic_dl/sites/hqbr.py
comic_dl/sites/japscan.py
comic_dl/sites/kissmanga.py
comic_dl/sites/lectortmo.py
comic_dl/sites/mangaFox.py
comic_dl/sites/mangaHere.py
comic_dl/sites/mangaReader.py
comic_dl/sites/mangadex.py
comic_dl/sites/manganelo.py
comic_dl/sites/mangatoonMobi.py
comic_dl/sites/omgBeauPeep.py
comic_dl/sites/quiremanhua.py
comic_dl/sites/rawSenManga.py
comic_dl/sites/readComicBooksOnline.py
comic_dl/sites/readComicsIO.py
comic_dl/sites/readComicsWebsite.py
comic_dl/sites/readcomicOnlineli.py
comic_dl/sites/stripUtopia.py
comic_dl/sites/webtoons.py