Metadata-Version: 2.1
Name: comic-dl
Version: 2024.2.10
Summary: Comic-dl is a command line tool to download Comics and Manga from various Manga and Comic sites easily.
Home-page: https://github.com/Xonshiz/comic-dl
Author: Xonshiz
Author-email: xonshiz@gmail.com
License: UNKNOWN
Keywords: comic-dl,cli,comic downloader,manga downloader,mangafox,batoto,kissmanga,comic naver,readcomiconline
Platform: UNKNOWN
Classifier: Development Status :: 5 - Production/Stable
Classifier: Environment :: Console
Classifier: Intended Audience :: End Users/Desktop
Classifier: License :: Public Domain
Classifier: Natural Language :: English
Classifier: Programming Language :: Python :: 3
Classifier: Programming Language :: Python :: 3.2
Classifier: Programming Language :: Python :: 3.3
Classifier: Programming Language :: Python :: 3.4
Classifier: Programming Language :: Python :: 3.5
Classifier: Programming Language :: Python :: 3.6
Classifier: Programming Language :: Python :: 3.7
Classifier: Programming Language :: Python :: 3.8
Classifier: Programming Language :: Python :: 3.9
Classifier: Operating System :: OS Independent
Classifier: Topic :: Multimedia :: Graphics
License-File: LICENSE
